hello_world/__init__.py
77_myfirst_hw_library_77-0.1.0.dist-info/METADATA
77_myfirst_hw_library_77-0.1.0.dist-info/WHEEL
77_myfirst_hw_library_77-0.1.0.dist-info/top_level.txt
77_myfirst_hw_library_77-0.1.0.dist-info/RECORD
